README.md
setup.cfg
setup.py
to_php_post_arr/__init__.py
to_php_post_arr/convert.py
to_php_post_arr.egg-info/PKG-INFO
to_php_post_arr.egg-info/SOURCES.txt
to_php_post_arr.egg-info/dependency_links.txt
to_php_post_arr.egg-info/top_level.txt