Metadata-Version: 1.1
Name: to-php-post-arr
Version: 0.0.1
Summary: Convert dict/list/nested to PHP Array like urlencoded string
Home-page: https://github.com/Viky-zhang/to_php_post_arr
Author: VikyZhang
Author-email: zwj_fhys@qq.com
License: MIT
Keywords: post php array
Platform: UNKNOWN
Classifier: Development Status :: 4 - Beta
Classifier: Intended Audience :: Developers
Classifier: Topic :: Software Development :: Build Tools
Classifier: License :: OSI Approved :: MIT License
Classifier: Programming Language :: Python :: 2.6
Classifier: Programming Language :: Python :: 2.7
Classifier: Programming Language :: Python :: 3
Classifier: Programming Language :: Python :: 3.3
Classifier: Programming Language :: Python :: 3.4
Classifier: Programming Language :: Python :: 3.5
